{"titulo": "Mec\u00e1nico soldador", "descripcion": ["\n", "<li><h3 class=\"mt0\">Descripci\u00f3n</h3></li>", "\n", "<li>Se solicita soldador con deseos de superacion ,para trabajar de manera inmediata,proactivo,responsable.<br/><br/>Favor de aplicar si se tiene la experiancia en el area solicitada</li>", "\n", "<li><h3>Requerimientos</h3></li>", "\n", "<li>Educaci\u00f3n M\u00ednima: Bachillerato / Educaci\u00f3n Media</li>", "<li>Disponibilidad de Viajar: No</li>", "<li>Disponibilidad de Cambio de Residencia: No</li>", "<li> </li>", "\n"], "fecha agregado": "2021-01-22 19:10:28.438097", "salario": ["salario", "no especificado"], "region": ["region ", "Santiago,"], "ciudad": ["ciudad", "Santiago\u00a0\u00b7"], "hora": ["hora", "31 agosto"]}