{"titulo": "Vendedor Repuestos  para Santiago", "descripcion": ["\n", "<li><h3 class=\"mt0\">Descripci\u00f3n</h3></li>", "\n", "<li>Buscamos vendedor con experiencia en el area de venta de Repuestos nuevo y usado de la marca Hyndai y Kia.<br/><br/>Descrpcion del puesto:  Experiencia en el area de vena de Repuestos y buen conocimiento del area a ejercer.<br/><br/>Aptitudes:  Capacidad de adaptacion, habilidades comunicativa, competencia deigitales, essfuerzo y lealtad, habilidades organizativa, trabajo en equipo y pro-actividad.<br/><br/>Nivel Academico:  Bachiller o Universitario.<br/><br/>Conocimiento informaticos:  Manejo de Office.<br/><br/>Experiencia:  4 a\u00f1os de experiencia en el area de ventas de Repuestos de Vehiculos.<br/><br/>Edad:  25-32 a\u00f1os<br/><br/>Horario:  Lunes a Viernes de 8:00 am  a 6:00 pm y los Sabados8:00 am a 12:00 pm<br/><br/>Salario:  RD$18,000.00 +  seguro de ley,+ comisiones por ventas.</li>", "\n", "<li><h3>Requerimientos</h3></li>", "\n", "<li>Educaci\u00f3n M\u00ednima: Universidad</li>", "<li>A\u00f1os de experiencia: 4</li>", "<li>Disponibilidad de Viajar: No</li>", "<li>Disponibilidad de Cambio de Residencia: No</li>", "<li> </li>", "\n"], "fecha agregado": "2021-01-22 19:08:59.762934", "salario": ["salario", "18.000,00 $ (Neto mensual)\u00a0\u00b7"], "region": ["region ", "Santiago,"], "ciudad": ["ciudad", "Santiago\u00a0\u00b7"], "hora": ["hora", "6 octubre"]}