{"titulo": "Asistente Administrativo - turno diurno", "descripcion": ["\n", "<li><h3 class=\"mt0\">Descripci\u00f3n</h3></li>", "\n", "<li>ASISTENTE ADMINISTRATIVO<br/><br/>Empresa dedicada a la prestaci\u00f3n de servicio web solicita personal calificado en el \u00e1rea administrativa de la empresa.<br/><br/>Funciones:<br/><br/>\u2022\tComunicaci\u00f3n efectiva ente usuarios y proveedores.<br/><br/>\u2022\tAtenci\u00f3n al cliente v\u00eda telef\u00f3nica y en redes sociales.<br/><br/>\u2022\tSeguimiento de carta de clientes, cobranza, pagos, ventas, entre otras actividades inherentes al cargo.<br/><br/>De se sexo femenino, de preferencia venezolana (necesita llevar las redes sociales de Venezuela desde RD), de edad comprendida entre 20 a 32 a\u00f1os.<br/><br/>Debe ser proactiva, tener buena actitud, buena presencia, capacidad de organizaci\u00f3n, planificaci\u00f3n y an\u00e1lisis, toma de decisiones, liderazgo.<br/><br/>Debe tener conocimiento del paquete office, en manejo de redes sociales, excelente redacci\u00f3n y dicci\u00f3n.<br/><br/>Para laborar de lunes a viernes de 8:00 am a 5:00 pm y s\u00e1bado hasta medio d\u00eda.<br/><br/></li>", "\n", "<li><h3>Requerimientos</h3></li>", "\n", "<li>Educaci\u00f3n M\u00ednima: Bachillerato / Educaci\u00f3n Media</li>", "<li>Idiomas: Espa\u00f1ol </li>", "<li>Edad: entre 20 y 32 a\u00f1os</li>", "<li>Conocimientos: Microsoft Excel, Microsoft PowerPoint, Microsoft Word, Windows, Organizaci\u00f3n, Planificaci\u00f3n, Trabajo en equipo, Redes, Microsoft Office</li>", "<li>Disponibilidad de Viajar: No</li>", "<li>Disponibilidad de Cambio de Residencia: No</li>", "\n"], "fecha agregado": "2021-01-22 19:06:29.310020", "salario": ["salario", "12.000,00 $ (Neto mensual)\u00a0\u00b7"], "region": ["region ", "Santo Domingo Oeste,"], "ciudad": ["ciudad", "Santo Domingo\u00a0\u00b7"], "hora": ["hora", "5 enero"]}