{"titulo": "Promotor de ventas Medio Tiempo", "descripcion": ["\n", "<li><h3 class=\"mt0\">Descripci\u00f3n</h3></li>", "\n", "<li>Realizar promotorias de celulares las cuales ayudan a impulsar las ventas.                                                                                </li>", "\n", "<li><h3>Requerimientos</h3></li>", "\n", "<li>Educaci\u00f3n M\u00ednima: Bachillerato / Educaci\u00f3n Media</li>", "<li>Edad: entre 20 y 30 a\u00f1os</li>", "<li>Disponibilidad de Viajar: No</li>", "<li>Disponibilidad de Cambio de Residencia: No</li>", "\n"], "fecha agregado": "2021-01-22 19:05:52.178929", "salario": ["salario", "12.000,00 $ (Neto mensual)\u00a0\u00b7"], "region": ["region ", "Santo Domingo Este,"], "ciudad": ["ciudad", "Santo Domingo\u00a0\u00b7"], "hora": ["hora", "13 enero (actualizada)"]}