{"titulo": "Ventas en el exterior", "descripcion": ["\n", "<li><h3 class=\"mt0\">Descripci\u00f3n</h3></li>", "\n", "<li>Empresa Americana Ofrece una oportunidad \u00fanica de emprendimiento , como representante de ventas, con o sin experiencia. Brindamos la capacitaci\u00f3n necesaria a nuestro personal. No manejamos esta oportunidad de manera convencional, vamos m\u00e1s all\u00e1 en b\u00fasqueda de personas emprendedoras con motivaci\u00f3n, optimismo, dispuesta a emprender y formar su propio equipo de trabajo. </li>", "\n", "<li><h3>Requerimientos</h3></li>", "\n", "<li>Educaci\u00f3n M\u00ednima: Educaci\u00f3n T\u00e9cnico/Profesional</li>", "<li>A\u00f1os de experiencia: 1</li>", "<li>Edad: entre 25 y 45 a\u00f1os</li>", "<li>Conocimientos: Direcci\u00f3n de ventas, Gesti\u00f3n de ventas, Marketing, Comercio exterior</li>", "<li>Disponibilidad de Viajar: Si</li>", "<li>Disponibilidad de Cambio de Residencia: Si</li>", "\n"], "fecha agregado": "2021-01-22 19:03:27.021658", "salario": ["salario", "137.000,00 $ (Neto mensual)\u00a0\u00b7"], "region": ["region ", "San Crist\u00f3bal,"], "ciudad": ["ciudad", "San Crist\u00f3bal\u00a0\u00b7"], "hora": ["hora", "21 enero"]}