{"titulo": "Encargado de Limpieza y Mantenimiento para Santo Domingo", "descripcion": ["\n", "<li><h3 class=\"mt0\">Descripci\u00f3n</h3></li>", "\n", "<li>Buscamos para la Santiago Encargado de Limpieza y Mantenimiento.<br/><br/>Descripcion del puesto:  Debe encargarse de la limpieza del local, mantener la higiene y dar soporte a manenimiento.<br/><br/>Aptitudes:  Flexibilidad, cratividad, comunicacion digital, aprendizaje.<br/><br/>Nivel academico:  Bachiller<br/><br/>Sexo:  Indistinto<br/><br/>Edad:  hasta 50 a\u00f1os<br/><br/>Horario:  8:00 am a 5:00 Pm<br/><br/>Beneficios Generales:  Todps los beneficio de ley, salario minimo</li>", "\n", "<li><h3>Requerimientos</h3></li>", "\n", "<li>Educaci\u00f3n M\u00ednima: Bachillerato / Educaci\u00f3n Media</li>", "<li>A\u00f1os de experiencia: 2</li>", "<li>Disponibilidad de Viajar: No</li>", "<li>Disponibilidad de Cambio de Residencia: No</li>", "<li> </li>", "\n"], "fecha agregado": "2021-01-22 19:08:57.165355", "salario": ["salario", "18.001,00 $ (Neto mensual)\u00a0\u00b7"], "region": ["region ", "Santiago,"], "ciudad": ["ciudad", "Santiago\u00a0\u00b7"], "hora": ["hora", "6 octubre"]}